hydra_plugins/hydra_ext_sweeper/__init__.py
hydra_plugins/hydra_ext_sweeper/ext_sweeper.py
hydra_plugins/hydra_ext_sweeper/py.typed
hydra_ext_sweeper-0.1.1.dist-info/METADATA
hydra_ext_sweeper-0.1.1.dist-info/WHEEL
hydra_ext_sweeper-0.1.1.dist-info/RECORD
